pa1/part-b/src/sbox.v
module sbox (inp, outp);

    input [3:0] inp; // wire since not specified, MSB FIRST SINCE 3:0!
    output [3:0] outp; // wire since not specified 

    reg [3:0] outp; // now declared as a reg.
    

// implement the SBox design based on the truth table / boolean equations provided
// you can either use a high level concurrency construct or you can use continuous assignments
    always @(*) begin
        outp[3] = (inp[3]&inp[2]&inp[0]) ^ (inp[3]&inp[1]&inp[0]) ^ inp[3] ^ (inp[2]&inp[1]&inp[0]) ^ (inp[2]&inp[1]) ^ inp[1] ^ inp[0] ^ 1'b1;
        outp[2] = (inp[3]&inp[2]&inp[0]) ^ (inp[3]&inp[1]&inp[0]) ^ (inp[3]&inp[1]) ^ (inp[3]&inp[0]) ^ inp[3] ^ inp[2] ^ (inp[1]&inp[0]) ^ 1'b1;
        outp[1] = (inp[3]&inp[2]&inp[0]) ^ (inp[3]&inp[2]) ^ (inp[3]&inp[1]&inp[0]) ^ (inp[3]&inp[1]) ^ inp[3] ^ (inp[2]&inp[1]&inp[0]) ^ inp[1];
        outp[0] = inp[3] ^ (inp[2]&inp[1]) ^ inp[2] ^ inp[0];
    end

endmodule

pa1/part-a/src/tb_sbox.v
`timescale 1ns / 1ps
module tb_sbox;

// testbench signals
reg [3:0] inp;
wire [3:0] outp;

// instantiate the S-box module

sbox DUT (
    .inp(inp),
    .outp(outp)
);

initial begin
    // display header
    $display("Time\t Input\t Output");
    // monitor changes in inp and outp
    $monitor("%0dns\t %b\t %b", $time, inp, outp);

    inp = 0;
    // stimulate the inp signal after a certain delay
    // test all possible values for inp signal
    
    inp = 4'h0; #10;
    if (outp !== 4'hC) $display("FAIL at inp=%h", inp);
    else $display("PASS at inp=%h", inp);

    inp = 4'h1; #10;
    if (outp !== 4'h5) $display("FAIL at inp=%h", inp);
    else $display("PASS at inp=%h", inp);

    inp = 4'h2; #10;
    if (outp !== 4'h6) $display("FAIL at inp=%h", inp);
    else $display("PASS at inp=%h", inp);

    inp = 4'h3; #10;
    if (outp !== 4'hB) $display("FAIL at inp=%h", inp);
    else $display("PASS at inp=%h", inp);

    inp = 4'h4; #10;
    if (outp !== 4'h9) $display("FAIL at inp=%h", inp);
    else $display("PASS at inp=%h", inp);

    inp = 4'h5; #10;
    if (outp !== 4'h0) $display("FAIL at inp=%h", inp);
    else $display("PASS at inp=%h", inp);

    inp = 4'h6; #10;
    if (outp !== 4'hA) $display("FAIL at inp=%h", inp);
    else $display("PASS at inp=%h", inp);

    inp = 4'h7; #10;
    if (outp !== 4'hD) $display("FAIL at inp=%h", inp);
    else $display("PASS at inp=%h", inp);

    inp = 4'h8; #10;
    if (outp !== 4'h3) $display("FAIL at inp=%h", inp);
    else $display("PASS at inp=%h", inp);

    inp = 4'h9; #10;
    if (outp !== 4'hE) $display("FAIL at inp=%h", inp);
    else $display("PASS at inp=%h", inp);

    inp = 4'hA; #10;
    if (outp !== 4'hF) $display("FAIL at inp=%h", inp);
    else $display("PASS at inp=%h", inp);

    inp = 4'hB; #10;
    if (outp !== 4'h8) $display("FAIL at inp=%h", inp);
    else $display("PASS at inp=%h", inp);

    inp = 4'hC; #10;
    if (outp !== 4'h4) $display("FAIL at inp=%h", inp);
    else $display("PASS at inp=%h", inp);

    inp = 4'hD; #10;
    if (outp !== 4'h7) $display("FAIL at inp=%h", inp);
    else $display("PASS at inp=%h", inp);

    inp = 4'hE; #10;
    if (outp !== 4'h1) $display("FAIL at inp=%h", inp);
    else $display("PASS at inp=%h", inp);

    inp = 4'hF; #10;
    if (outp !== 4'h2) $display("FAIL at inp=%h", inp);
    else $display("PASS at inp=%h", inp);

    #10;
    $display("\nsimulation over.");


    // finish simulation
    $finish;
end

initial begin
    $dumpfile("sbox_dump.vcd");
    $dumpvars(1, tb_sbox);
end

endmodule

pa1/part-a/src/sbox_dump.vcd
$date
	Tue Jan 20 06:49:57 2026
$end
$version
	Icarus Verilog
$end
$timescale
	1ps
$end
$scope module tb_sbox $end
$var wire 4 ! outp [3:0] $end
$var reg 4 " inp [3:0] $end
$upscope $end
$enddefinitions $end
$comment Show the parameter values. $end
$dumpall
$end
#0
$dumpvars
b0 "
b1100 !
$end
#10000
b101 !
b1 "
#20000
b110 !
b10 "
#30000
b1011 !
b11 "
#40000
b1001 !
b100 "
#50000
b0 !
b101 "
#60000
b1010 !
b110 "
#70000
b1101 !
b111 "
#80000
b11 !
b1000 "
#90000
b1110 !
b1001 "
#100000
b1111 !
b1010 "
#110000
b1000 !
b1011 "
#120000
b100 !
b1100 "
#130000
b111 !
b1101 "
#140000
b1 !
b1110 "
#150000
b10 !
b1111 "
