pa1/part-b/src/present_cipher.v

// =========================================================

// PRESENT - a lightweight block cipher design
// NOTE: DO NOT modify the present_cipher module.
//       Make changes only to the present_datapath, present_keyschedule and perm modules.

// =========================================================

module present_cipher (clk, rst, plaintext, key, en, prdy, krdy, start, done, ciphertext);

input clk, rst;
input [63:0] plaintext;         // 64-bit plaintext
input [79:0] key;               // 80-bit encryption key
input en;                       // enable signal for controller
input prdy, krdy;               // plaintext and key ready or available
output start, done;             // control signals
output [63:0] ciphertext;       // 64-bit ciphertext

reg [63:0] ciphertext;
reg start, done;

// controller signals
reg [4:0] round_counter;        // counter for encryption round
reg [63:0] pstate;              // plaintext state reg
reg [79:0] kstate;              // round key state reg

// datapath signals
wire [63:0] pstate_nxt;         // next state for plaintext
wire [79:0] kstate_nxt;         // next state for key update
wire [63:0] nxt_rkey;           // next round key

// detect final round one cycle early
wire final_round = (round_counter == 30);

// instantiating the present_datapath module
present_datapath dpath ( .pstate_in(pstate), .kstate_in(kstate), .round_counter(round_counter), .pstate_out(pstate_nxt), .kstate_out(kstate_nxt), .rkey(nxt_rkey) );

// controller design
always @(posedge clk or posedge rst) begin
    if (rst == 1) begin
        // initialize the signals
        pstate <= 64'h0000000000000000;
        kstate <= 80'h00000000000000000000;
        ciphertext <= 64'h0000000000000000;
        round_counter <= 5'b00000;
        start <= 0;
        done <= 0;
    end
    else if (en) begin
        if (!start) begin
            // proceed only if plaintext and key ready signals are high
            if (krdy && prdy) begin
                kstate <= key;
                pstate <= plaintext;
                done <= 0;
                start <= 1;
            end
        end
        else if (start) begin
            // check for round 30 instead of 31
            if (final_round) begin
                // on the next cycle, round_counter will be 31
                round_counter <= round_counter + 1;
                pstate <= pstate_nxt;
                kstate <= kstate_nxt;
            end
            else if (round_counter == 31) begin
                // this will execute one cycle after final_round == 1
                kstate <= key;
                round_counter <= 5'b00000;  // reset counter for next encryption
                ciphertext <= pstate ^ nxt_rkey;
                start <= 0;
                done <= 1;
            end
            else begin
                // update the round counter and next states for plaintext and key update
                round_counter <= round_counter + 1;
                pstate <= pstate_nxt;
                kstate <= kstate_nxt;
            end
        end
    end
end

endmodule

// =========================================================

// datapath module for PRESENT cipher
// NOTE: DO NOT make any change to the interface signals.
module present_datapath (pstate_in, kstate_in, round_counter, pstate_out, kstate_out, rkey);

input [63:0] pstate_in;         // plaintext state input
input [79:0] kstate_in;         // key update state input
input [4:0] round_counter;      // counter for encryption round
output [63:0] pstate_out;       // next state for plaintext
output [79:0] kstate_out;       // next state for key update
output [63:0] rkey;             // next round key

// ===== DO NOT MODIFY ANYTHING ABOVE THIS =====

// declare any necessary wires/reg
wire [63:0] sbox_inp;
wire [63:0] sbox_out;
//wire [63:0] perm_out;

// instantiate your present_keyschedule module to change the next state of key update and next round key

present_keyschedule ks (
    .kstate_in(kstate_in),
    .round_counter(round_counter),
    .kstate_out(kstate_out),
    .rkey(rkey)
);

// add round key to the plaintext state input
assign sbox_inp = pstate_in ^ rkey;

// perform sbox operation, instantiate the sbox module

genvar i;
generate
    for (i = 0; i < 16; i = i + 1) begin : sbox_layer
        wire [3:0] sbox_inp_i;
        wire [3:0] sbox_out_i;

        sbox u_sbox (
            .inp (sbox_inp[4*i+3 : 4*i]),
            .outp(sbox_out_i)
        );
        assign sbox_out[4*i+3:4*i] = sbox_out_i;
    end
endgenerate

// perform bit-permutation operation, instantiate the bit-permutation module

perm p0 (
    .state_in (sbox_out),
    .state_out(pstate_out)
);

endmodule

// =========================================================

// datapath module for key schedule
// NOTE: DO NOT make any change to the interface signals.
module present_keyschedule ( kstate_in, round_counter, kstate_out, rkey);

input [79:0] kstate_in;             // key update state input
input [4:0] round_counter;          // counter for encryption round
output [79:0] kstate_out;           // next state for key update
output [63:0] rkey;                 // next round key

// ===== DO NOT MODIFY ANYTHING ABOVE THIS =====

// declare any necessary wires/reg

wire [79:0] rotated;
wire [3:0] sbox_out; // instantiating sbox for bits [79:76] of the rotated key state
wire [79:0] after_sbox;

// generate the next round key from the current key update state
assign rkey = kstate_in[79:16];

// perform the key update operation
// use the concatenation operator for the 1st step

assign rotated = {kstate_in[18:0],kstate_in[79:19]}; // rotate by 61 bits(right rotate by 19 bits), {a, b} -> concatenation of a(msb)&b

// for 2nd step, perform sbox operation on 79 to 76 bits of key state

sbox s0 (.inp(rotated[79:76]), .outp(sbox_out));

assign after_sbox = {sbox_out, rotated[75:0]};

// NOTE: for the 3rd step in key update, xor the 19 to 15 bits with (round_counter + 1), instead of round_counter

// top chunk -> 60 bits, unchanged
// middle chunk -> 5 bits(XORed)
// bottom chunk -> 15 bits, unchanged

assign kstate_out = {
    after_sbox[79:20],
    after_sbox[19:15] ^ (round_counter + 5'd1),
    after_sbox[14:0]
};

endmodule

// =========================================================

// datapath module for bit-permutation
// NOTE: DO NOT make any change to the interface signals.
module perm (state_in, state_out);

input [63:0] state_in;          // input state
output [63:0] state_out;        // output state

// ===== DO NOT MODIFY ANYTHING ABOVE THIS =====

// declare any necessary wires/reg
genvar i;
// perform the bit-permutation operation by either using high level constructs for concurrency or continuous assignments

generate
    for (i = 0; i < 64; i = i + 1) begin : perm_loop
        assign state_out[16*(i%4) + i/4] = state_in[i];
    end
endgenerate

endmodule
// =========================================================

pa1/part-b/src/sbox.v
module sbox (inp, outp);

    input [3:0] inp; // wire since not specified, MSB FIRST SINCE 3:0!
    output [3:0] outp; // wire since not specified 

    reg [3:0] outp; // now declared as a reg.
    

// implement the SBox design based on the truth table / boolean equations provided
// you can either use a high level concurrency construct or you can use continuous assignments
    always @(*) begin
        outp[3] = (inp[3]&inp[2]&inp[0]) ^ (inp[3]&inp[1]&inp[0]) ^ inp[3] ^ (inp[2]&inp[1]&inp[0]) ^ (inp[2]&inp[1]) ^ inp[1] ^ inp[0] ^ 1'b1;
        outp[2] = (inp[3]&inp[2]&inp[0]) ^ (inp[3]&inp[1]&inp[0]) ^ (inp[3]&inp[1]) ^ (inp[3]&inp[0]) ^ inp[3] ^ inp[2] ^ (inp[1]&inp[0]) ^ 1'b1;
        outp[1] = (inp[3]&inp[2]&inp[0]) ^ (inp[3]&inp[2]) ^ (inp[3]&inp[1]&inp[0]) ^ (inp[3]&inp[1]) ^ inp[3] ^ (inp[2]&inp[1]&inp[0]) ^ inp[1];
        outp[0] = inp[3] ^ (inp[2]&inp[1]) ^ inp[2] ^ inp[0];
    end

endmodule

pa1/part-b/src/tb_present_cipher.v
`timescale 1ns / 1ps
module tb_present_cipher;

reg clk;
reg rst;
reg [63:0] plaintext;
reg [79:0] key;
reg en;
reg krdy;
reg prdy;

wire [63:0] ciphertext;
wire done;
wire start;


always begin
    #5 clk = ~clk;
end

present_cipher dut ( .clk(clk), .rst(rst), .plaintext(plaintext), .key(key), .en(en), .prdy(prdy), .krdy(krdy),
                        .done(done), .start(start), .ciphertext(ciphertext) );

initial begin
    $display ("time\t, clk\t, rst\t plaintext\t, key\t, ciphertext\t, en\t, krdy\t, prdy\t, start\t, done\t" );
    $monitor ("%g\t %b\t, %b\t %x\t   %x\t  %x\t  %b\t \%b\t  %b\t %b\t %b\t",
                $time, clk, rst, plaintext, key, ciphertext, en, krdy, prdy, start, done);

    clk = 1;
    #10 rst = 1;
    #10 rst = 0;
    #10 plaintext <= 64'hffffffffffffffff;      // ciphertext = ad7d5befea5c6dea
    // plaintext <= 64'h1000000000000000;      // ciphertext = b5cafa95bee34f40
    key <= 80'h10000000000000000000;

    #10 en = 1;
    #10 krdy <= 1;
    #10 prdy <= 1;

    #10 krdy <= 0;
    #10 prdy <= 0;

    #500 $finish;
end

initial begin
    $dumpfile ("present_dump.vcd");
    $dumpvars (1, tb_present_cipher);
end

endmodule

pa1/part-b/src/present_dump.vcd
$date
	Sat Feb 28 02:01:47 2026
$end
$version
	Icarus Verilog
$end
$timescale
	1ps
$end
$scope module tb_present_cipher $end
$var wire 1 ! start $end
$var wire 1 " done $end
$var wire 64 # ciphertext [63:0] $end
$var reg 1 $ clk $end
$var reg 1 % en $end
$var reg 80 & key [79:0] $end
$var reg 1 ' krdy $end
$var reg 64 ( plaintext [63:0] $end
$var reg 1 ) prdy $end
$var reg 1 * rst $end
$upscope $end
$enddefinitions $end
$comment Show the parameter values. $end
$dumpall
$end
#0
$dumpvars
x*
x)
bx (
x'
bx &
x%
1$
bx #
x"
x!
$end
#5000
0$
#10000
0"
0!
b0 #
1$
1*
#15000
0$
#20000
1$
0*
#25000
0$
#30000
b10000000000000000000000000000000000000000000000000000000000000000000000000000 &
b1111111111111111111111111111111111111111111111111111111111111111 (
1$
#35000
0$
#40000
1$
1%
#45000
0$
#50000
1'
1$
#55000
0$
#60000
1)
1$
#65000
0$
#70000
1!
0'
1$
#75000
0$
#80000
0)
1$
